one_convert-0.0.0.dist-info/licenses/LICENSE
oneconvert/__init__.py
oneconvert/converter.py
oneconvert/datasource/__init__.py
oneconvert/datasource/base.py
oneconvert/driver/__init__.py
one_convert-0.0.0.dist-info/METADATA
one_convert-0.0.0.dist-info/WHEEL
one_convert-0.0.0.dist-info/top_level.txt
one_convert-0.0.0.dist-info/RECORD
