Metadata-Version: 2.4
Name: one-convert
Version: 0.0.0
Summary: One Convert
Author: dengshaolin
License: Apache-2.0
Project-URL: Homepage, https://gitee.com/dengshaolin/one-convert
Project-URL: Bug Tracker, https://gitee.com/dengshaolin/one-convert/issues
Classifier: Intended Audience :: Information Technology
Classifier: Intended Audience :: System Administrators
Classifier: Operating System :: POSIX :: Linux
Classifier: Operating System :: Microsoft :: Windows
Classifier: Programming Language :: Python
Classifier: Programming Language :: Python :: 3 :: Only
Classifier: Programming Language :: Python :: 3
Classifier: Programming Language :: Python :: 3.9
Classifier: Programming Language :: Python :: 3.10
Classifier: Programming Language :: Python :: 3.11
Classifier: Programming Language :: Python :: 3.12
Classifier: Programming Language :: Python :: 3.13
Requires-Python: >=3.9
License-File: LICENSE
Dynamic: license-file
